README
setup.py
bambu_cron/__init__.py
bambu_cron/frequency.py
bambu_cron/middleware.py
bambu_cron/models.py
bambu_cron/options.py
bambu_cron/sites.py
bambu_cron/weekdays.py
bambu_cron.egg-info/PKG-INFO
bambu_cron.egg-info/SOURCES.txt
bambu_cron.egg-info/dependency_links.txt
bambu_cron.egg-info/requires.txt
bambu_cron.egg-info/top_level.txt
bambu_cron/management/__init__.py
bambu_cron/management/commands/__init__.py
bambu_cron/management/commands/cron.py
bambu_cron/migrations/0001_initial.py
bambu_cron/migrations/__init__.py