Metadata-Version: 1.1
Name: bambu-cron
Version: 2.0
Summary: A simple scheduling system that lets you define jobs that get performed at various intervals. Use a virtual "poor man's cron" or a single Django management command to run the jobs.
Home-page: https://github.com/iamsteadman/bambu-cron
Author: Steadman
Author-email: mark@steadman.io
License: UNKNOWN
Platform: UNKNOWN
Classifier: Development Status :: 4 - Beta
Classifier: Environment :: Web Environment
Classifier: Framework :: Django
